vearne_akshare_mcp/__init__.py
vearne_akshare_mcp/__main__.py
vearne_akshare_mcp/core/__init__.py
vearne_akshare_mcp/core/mcp_server.py
vearne_akshare_mcp/core/tools.py
vearne_akshare_mcp/data/us_stock_akshare_codes.csv
vearne_akshare_mcp/markets/__init__.py
vearne_akshare_mcp/markets/cn/__init__.py
vearne_akshare_mcp/markets/cn/api.py
vearne_akshare_mcp/markets/hk/__init__.py
vearne_akshare_mcp/markets/hk/api.py
vearne_akshare_mcp/markets/us/__init__.py
vearne_akshare_mcp/markets/us/api.py
vearne_akshare_mcp/news/__init__.py
vearne_akshare_mcp/news/eastmoney.py
vearne_akshare_mcp/news/scraper.py
vearne_akshare_mcp-0.2.2.dist-info/METADATA
vearne_akshare_mcp-0.2.2.dist-info/WHEEL
vearne_akshare_mcp-0.2.2.dist-info/entry_points.txt
vearne_akshare_mcp-0.2.2.dist-info/licenses/LICENSE
vearne_akshare_mcp-0.2.2.dist-info/RECORD
