Metadata-Version: 2.4
Name: vearne_akshare_mcp
Version: 0.2.2
Summary: An MCP server capable of retrieving A-share, Hong Kong stock, and U.S. stock data using AkShare.
Project-URL: Homepage, https://github.com/vearne/akshare-mcp
Author-email: vearne <asdwoshiaotian@gmail.com>
License: MIT
License-File: LICENSE
Requires-Python: >=3.8
Requires-Dist: akshare==1.17.19
Requires-Dist: fastmcp==2.10.5
Requires-Dist: playwright==1.55.0
Requires-Dist: pydantic==2.11.7
